sec_financial_data/__init__.py
sec_financial_data/patterns.py
sec_financial_data/sec_financial_data.py
sec_financial_data/stock_splits.py
sec_financial_data-0.1.4.dist-info/licenses/LICENSE
sec_financial_data-0.1.4.dist-info/METADATA
sec_financial_data-0.1.4.dist-info/WHEEL
sec_financial_data-0.1.4.dist-info/top_level.txt
sec_financial_data-0.1.4.dist-info/RECORD
