Metadata-Version: 2.4
Name: sec-financial-data
Version: 0.1.4
Summary: A Python package to retrieve financial data from SEC EDGAR.
Author-email: Arun Mittal <arun.mittal.sjsu@gmail.com>
Project-URL: Homepage, https://github.com/armittal89/sec_api
Project-URL: Bug Tracker, https://github.com/armittal89/sec_api/issues
Classifier: Programming Language :: Python :: 3
Classifier: Operating System :: OS Independent
Classifier: Intended Audience :: Developers
Classifier: Intended Audience :: Financial and Insurance Industry
Classifier: Topic :: Office/Business :: Financial
Classifier: Topic :: Software Development :: Libraries :: Python Modules
Requires-Python: >=3.7
License-File: LICENSE
Requires-Dist: requests>=2.20.0
Dynamic: license-file
